{
  "header": {
    "seq": 0,
    "stamp": {
      "sec": 0,
      "nsec": 0
    },
    "frame_id": "map"
  },
  "poses": [
    {
      "header": {
        "seq": 0,
        "stamp": {
          "sec": 0,
          "nsec": 0
        },
        "frame_id": "map"
      },
      "pose": {
        "position": {
          "x": 0.0,
          "y": 0.0,
          "z": 0.0
        },
        "orientation": {
          "x": 0.0,
          "y": 0.0,
          "z": 0.0,
          "w": 0.0
        }
      }
    },
    {
      "header": {
        "seq": 0,
        "stamp": {
          "sec": 0,
          "nsec": 0
        },
        "frame_id": "map"
      },
      "pose": {
        "position": {
          "x": -0.294075616940888,
          "y": -0.00493029416855395,
          "z": 0.0
        },
        "orientation": {
          "x": 0.0,
          "y": 0.0,
          "z": 0.0,
          "w": 0.0
        }
      }
    },
    {
      "header": {
        "seq": 0,
        "stamp": {
          "sec": 0,
          "nsec": 0
        },
        "frame_id": "map"
      },
      "pose": {
        "position": {
          "x": -0.3871205217359832,
          "y": -0.019667159339574858,
          "z": 0.0
        },
        "orientation": {
          "x": 0.0,
          "y": 0.0,
          "z": 0.0,
          "w": 0.0
        }
      }
    },
    {
      "header": {
        "seq": 0,
        "stamp": {
          "sec": 0,
          "nsec": 0
        },
        "frame_id": "map"
      },
      "pose": {
        "position": {
          "x": -0.4781152949374524,
          "y": -0.04404913533436172,
          "z": 0.0
        },
        "orientation": {
          "x": 0.0,
          "y": 0.0,
          "z": 0.0,
          "w": 0.0
        }
      }
    },
    {
      "header": {
        "seq": 0,
        "stamp": {
          "sec": 0,
          "nsec": 0
        },
        "frame_id": "map"
      },
      "pose": {
        "position": {
          "x": -0.5660629787682199,
          "y": -0.07780908812165899,
          "z": 0.0
        },
        "orientation": {
          "x": 0.0,
          "y": 0.0,
          "z": 0.0,
          "w": 0.0
        }
      }
    },
    {
      "header": {
        "seq": 0,
        "stamp": {
          "sec": 0,
          "nsec": 0
        },
        "frame_id": "map"
      },
      "pose": {
        "position": {
          "x": -0.6499999999999998,
          "y": -0.12057713659400515,
          "z": 0.0
        },
        "orientation": {
          "x": 0.0,
          "y": 0.0,
          "z": 0.0,
          "w": 0.0
        }
      }
    },
    {
      "header": {
        "seq": 0,
        "stamp": {
          "sec": 0,
          "nsec": 0
        },
        "frame_id": "map"
      },
      "pose": {
        "position": {
          "x": -0.7290067270632257,
          "y": -0.17188470506254727,
          "z": 0.0
        },
        "orientation": {
          "x": 0.0,
          "y": 0.0,
          "z": 0.0,
          "w": 0.0
        }
      }
    },
    {
      "header": {
        "seq": 0,
        "stamp": {
          "sec": 0,
          "nsec": 0
        },
        "frame_id": "map"
      },
      "pose": {
        "position": {
          "x": -0.8022175457229725,
          "y": -0.2311696570703452,
          "z": 0.0
        },
        "orientation": {
          "x": 0.0,
          "y": 0.0,
          "z": 0.0,
          "w": 0.0
        }
      }
    },
    {
      "header": {
        "seq": 0,
        "stamp": {
          "sec": 0,
          "nsec": 0
        },
        "frame_id": "map"
      },
      "pose": {
        "position": {
          "x": -0.8688303429296549,
          "y": -0.29778245427702776,
          "z": 0.0
        },
        "orientation": {
          "x": 0.0,
          "y": 0.0,
          "z": 0.0,
          "w": 0.0
        }
      }
    },
    {
      "header": {
        "seq": 0,
        "stamp": {
          "sec": 0,
          "nsec": 0
        },
        "frame_id": "map"
      },
      "pose": {
        "position": {
          "x": -0.9281152949374529,
          "y": -0.37099327293677453,
          "z": 0.0
        },
        "orientation": {
          "x": 0.0,
          "y": 0.0,
          "z": 0.0,
          "w": 0.0
        }
      }
    },
    {
      "header": {
        "seq": 0,
        "stamp": {
          "sec": 0,
          "nsec": 0
        },
        "frame_id": "map"
      },
      "pose": {
        "position": {
          "x": -0.9794228634059952,
          "y": -0.4500000000000004,
          "z": 0.0
        },
        "orientation": {
          "x": 0.0,
          "y": 0.0,
          "z": 0.0,
          "w": 0.0
        }
      }
    },
    {
      "header": {
        "seq": 0,
        "stamp": {
          "sec": 0,
          "nsec": 0
        },
        "frame_id": "map"
      },
      "pose": {
        "position": {
          "x": -1.0221909118783412,
          "y": -0.5339370212317803,
          "z": 0.0
        },
        "orientation": {
          "x": 0.0,
          "y": 0.0,
          "z": 0.0,
          "w": 0.0
        }
      }
    },
    {
      "header": {
        "seq": 0,
        "stamp": {
          "sec": 0,
          "nsec": 0
        },
        "frame_id": "map"
      },
      "pose": {
        "position": {
          "x": -1.0559508646656386,
          "y": -0.621884705062548,
          "z": 0.0
        },
        "orientation": {
          "x": 0.0,
          "y": 0.0,
          "z": 0.0,
          "w": 0.0
        }
      }
    },
    {
      "header": {
        "seq": 0,
        "stamp": {
          "sec": 0,
          "nsec": 0
        },
        "frame_id": "map"
      },
      "pose": {
        "position": {
          "x": -1.0803328406604253,
          "y": -0.7128794782640174,
          "z": 0.0
        },
        "orientation": {
          "x": 0.0,
          "y": 0.0,
          "z": 0.0,
          "w": 0.0
        }
      }
    },
    {
      "header": {
        "seq": 0,
        "stamp": {
          "sec": 0,
          "nsec": 0
        },
        "frame_id": "map"
      },
      "pose": {
        "position": {
          "x": -1.095069705831446,
          "y": -0.8059243830591128,
          "z": 0.0
        },
        "orientation": {
          "x": 0.0,
          "y": 0.0,
          "z": 0.0,
          "w": 0.0
        }
      }
    },
    {
      "header": {
        "seq": 0,
        "stamp": {
          "sec": 0,
          "nsec": 0
        },
        "frame_id": "map"
      },
      "pose": {
        "position": {
          "x": -1.1,
          "y": -0.9000000000000014,
          "z": 0.0
        },
        "orientation": {
          "x": 0.0,
          "y": 0.0,
          "z": 0.0,
          "w": 0.0
        }
      }
    },
    {
      "header": {
        "seq": 0,
        "stamp": {
          "sec": 0,
          "nsec": 0
        },
        "frame_id": "map"
      },
      "pose": {
        "position": {
          "x": -1.0950697058314458,
          "y": -0.9940756169408895,
          "z": 0.0
        },
        "orientation": {
          "x": 0.0,
          "y": 0.0,
          "z": 0.0,
          "w": 0.0
        }
      }
    },
    {
      "header": {
        "seq": 0,
        "stamp": {
          "sec": 0,
          "nsec": 0
        },
        "frame_id": "map"
      },
      "pose": {
        "position": {
          "x": -1.0803328406604247,
          "y": -1.087120521735985,
          "z": 0.0
        },
        "orientation": {
          "x": 0.0,
          "y": 0.0,
          "z": 0.0,
          "w": 0.0
        }
      }
    },
    {
      "header": {
        "seq": 0,
        "stamp": {
          "sec": 0,
          "nsec": 0
        },
        "frame_id": "map"
      },
      "pose": {
        "position": {
          "x": -1.0559508646656377,
          "y": -1.1781152949374543,
          "z": 0.0
        },
        "orientation": {
          "x": 0.0,
          "y": 0.0,
          "z": 0.0,
          "w": 0.0
        }
      }
    },
    {
      "header": {
        "seq": 0,
        "stamp": {
          "sec": 0,
          "nsec": 0
        },
        "frame_id": "map"
      },
      "pose": {
        "position": {
          "x": -1.02219091187834,
          "y": -1.2660629787682218,
          "z": 0.0
        },
        "orientation": {
          "x": 0.0,
          "y": 0.0,
          "z": 0.0,
          "w": 0.0
        }
      }
    },
    {
      "header": {
        "seq": 0,
        "stamp": {
          "sec": 0,
          "nsec": 0
        },
        "frame_id": "map"
      },
      "pose": {
        "position": {
          "x": -0.9794228634059938,
          "y": -1.3500000000000019,
          "z": 0.0
        },
        "orientation": {
          "x": 0.0,
          "y": 0.0,
          "z": 0.0,
          "w": 0.0
        }
      }
    },
    {
      "header": {
        "seq": 0,
        "stamp": {
          "sec": 0,
          "nsec": 0
        },
        "frame_id": "map"
      },
      "pose": {
        "position": {
          "x": -0.9281152949374514,
          "y": -1.4290067270632276,
          "z": 0.0
        },
        "orientation": {
          "x": 0.0,
          "y": 0.0,
          "z": 0.0,
          "w": 0.0
        }
      }
    },
    {
      "header": {
        "seq": 0,
        "stamp": {
          "sec": 0,
          "nsec": 0
        },
        "frame_id": "map"
      },
      "pose": {
        "position": {
          "x": -0.8688303429296533,
          "y": -1.502217545722974,
          "z": 0.0
        },
        "orientation": {
          "x": 0.0,
          "y": 0.0,
          "z": 0.0,
          "w": 0.0
        }
      }
    },
    {
      "header": {
        "seq": 0,
        "stamp": {
          "sec": 0,
          "nsec": 0
        },
        "frame_id": "map"
      },
      "pose": {
        "position": {
          "x": -0.8022175457229705,
          "y": -1.5688303429296564,
          "z": 0.0
        },
        "orientation": {
          "x": 0.0,
          "y": 0.0,
          "z": 0.0,
          "w": 0.0
        }
      }
    },
    {
      "header": {
        "seq": 0,
        "stamp": {
          "sec": 0,
          "nsec": 0
        },
        "frame_id": "map"
      },
      "pose": {
        "position": {
          "x": -0.7290067270632239,
          "y": -1.6281152949374542,
          "z": 0.0
        },
        "orientation": {
          "x": 0.0,
          "y": 0.0,
          "z": 0.0,
          "w": 0.0
        }
      }
    },
    {
      "header": {
        "seq": 0,
        "stamp": {
          "sec": 0,
          "nsec": 0
        },
        "frame_id": "map"
      },
      "pose": {
        "position": {
          "x": -0.6499999999999977,
          "y": -1.6794228634059962,
          "z": 0.0
        },
        "orientation": {
          "x": 0.0,
          "y": 0.0,
          "z": 0.0,
          "w": 0.0
        }
      }
    },
    {
      "header": {
        "seq": 0,
        "stamp": {
          "sec": 0,
          "nsec": 0
        },
        "frame_id": "map"
      },
      "pose": {
        "position": {
          "x": -0.5660629787682179,
          "y": -1.722190911878342,
          "z": 0.0
        },
        "orientation": {
          "x": 0.0,
          "y": 0.0,
          "z": 0.0,
          "w": 0.0
        }
      }
    },
    {
      "header": {
        "seq": 0,
        "stamp": {
          "sec": 0,
          "nsec": 0
        },
        "frame_id": "map"
      },
      "pose": {
        "position": {
          "x": -0.47811529493745036,
          "y": -1.755950864665639,
          "z": 0.0
        },
        "orientation": {
          "x": 0.0,
          "y": 0.0,
          "z": 0.0,
          "w": 0.0
        }
      }
    },
    {
      "header": {
        "seq": 0,
        "stamp": {
          "sec": 0,
          "nsec": 0
        },
        "frame_id": "map"
      },
      "pose": {
        "position": {
          "x": -0.3871205217359811,
          "y": -1.7803328406604257,
          "z": 0.0
        },
        "orientation": {
          "x": 0.0,
          "y": 0.0,
          "z": 0.0,
          "w": 0.0
        }
      }
    },
    {
      "header": {
        "seq": 0,
        "stamp": {
          "sec": 0,
          "nsec": 0
        },
        "frame_id": "map"
      },
      "pose": {
        "position": {
          "x": -0.2940756169408858,
          "y": -1.7950697058314464,
          "z": 0.0
        },
        "orientation": {
          "x": 0.0,
          "y": 0.0,
          "z": 0.0,
          "w": 0.0
        }
      }
    },
    {
      "header": {
        "seq": 0,
        "stamp": {
          "sec": 0,
          "nsec": 0
        },
        "frame_id": "map"
      },
      "pose": {
        "position": {
          "x": -0.19999999999999776,
          "y": -1.8,
          "z": 0.0
        },
        "orientation": {
          "x": 0.0,
          "y": 0.0,
          "z": 0.0,
          "w": 0.0
        }
      }
    },
    {
      "header": {
        "seq": 0,
        "stamp": {
          "sec": 0,
          "nsec": 0
        },
        "frame_id": "map"
      },
      "pose": {
        "position": {
          "x": -0.10592438305910971,
          "y": -1.7950697058314458,
          "z": 0.0
        },
        "orientation": {
          "x": 0.0,
          "y": 0.0,
          "z": 0.0,
          "w": 0.0
        }
      }
    },
    {
      "header": {
        "seq": 0,
        "stamp": {
          "sec": 0,
          "nsec": 0
        },
        "frame_id": "map"
      },
      "pose": {
        "position": {
          "x": -0.012879478264014532,
          "y": -1.7803328406604246,
          "z": 0.0
        },
        "orientation": {
          "x": 0.0,
          "y": 0.0,
          "z": 0.0,
          "w": 0.0
        }
      }
    },
    {
      "header": {
        "seq": 0,
        "stamp": {
          "sec": 0,
          "nsec": 0
        },
        "frame_id": "map"
      },
      "pose": {
        "position": {
          "x": 0.07811529493745462,
          "y": -1.7559508646656377,
          "z": 0.0
        },
        "orientation": {
          "x": 0.0,
          "y": 0.0,
          "z": 0.0,
          "w": 0.0
        }
      }
    },
    {
      "header": {
        "seq": 0,
        "stamp": {
          "sec": 0,
          "nsec": 0
        },
        "frame_id": "map"
      },
      "pose": {
        "position": {
          "x": 0.16606297876822196,
          "y": -1.72219091187834,
          "z": 0.0
        },
        "orientation": {
          "x": 0.0,
          "y": 0.0,
          "z": 0.0,
          "w": 0.0
        }
      }
    },
    {
      "header": {
        "seq": 0,
        "stamp": {
          "sec": 0,
          "nsec": 0
        },
        "frame_id": "map"
      },
      "pose": {
        "position": {
          "x": 0.2500000000000016,
          "y": -1.679422863405994,
          "z": 0.0
        },
        "orientation": {
          "x": 0.0,
          "y": 0.0,
          "z": 0.0,
          "w": 0.0
        }
      }
    },
    {
      "header": {
        "seq": 0,
        "stamp": {
          "sec": 0,
          "nsec": 0
        },
        "frame_id": "map"
      },
      "pose": {
        "position": {
          "x": 0.3290067270632275,
          "y": -1.6281152949374516,
          "z": 0.0
        },
        "orientation": {
          "x": 0.0,
          "y": 0.0,
          "z": 0.0,
          "w": 0.0
        }
      }
    },
    {
      "header": {
        "seq": 0,
        "stamp": {
          "sec": 0,
          "nsec": 0
        },
        "frame_id": "map"
      },
      "pose": {
        "position": {
          "x": 0.4022175457229738,
          "y": -1.5688303429296535,
          "z": 0.0
        },
        "orientation": {
          "x": 0.0,
          "y": 0.0,
          "z": 0.0,
          "w": 0.0
        }
      }
    },
    {
      "header": {
        "seq": 0,
        "stamp": {
          "sec": 0,
          "nsec": 0
        },
        "frame_id": "map"
      },
      "pose": {
        "position": {
          "x": 0.46883034292965614,
          "y": -1.502217545722971,
          "z": 0.0
        },
        "orientation": {
          "x": 0.0,
          "y": 0.0,
          "z": 0.0,
          "w": 0.0
        }
      }
    },
    {
      "header": {
        "seq": 0,
        "stamp": {
          "sec": 0,
          "nsec": 0
        },
        "frame_id": "map"
      },
      "pose": {
        "position": {
          "x": 0.5281152949374539,
          "y": -1.4290067270632243,
          "z": 0.0
        },
        "orientation": {
          "x": 0.0,
          "y": 0.0,
          "z": 0.0,
          "w": 0.0
        }
      }
    },
    {
      "header": {
        "seq": 0,
        "stamp": {
          "sec": 0,
          "nsec": 0
        },
        "frame_id": "map"
      },
      "pose": {
        "position": {
          "x": 0.5794228634059959,
          "y": -1.3499999999999983,
          "z": 0.0
        },
        "orientation": {
          "x": 0.0,
          "y": 0.0,
          "z": 0.0,
          "w": 0.0
        }
      }
    },
    {
      "header": {
        "seq": 0,
        "stamp": {
          "sec": 0,
          "nsec": 0
        },
        "frame_id": "map"
      },
      "pose": {
        "position": {
          "x": 0.6221909118783417,
          "y": -1.2660629787682183,
          "z": 0.0
        },
        "orientation": {
          "x": 0.0,
          "y": 0.0,
          "z": 0.0,
          "w": 0.0
        }
      }
    },
    {
      "header": {
        "seq": 0,
        "stamp": {
          "sec": 0,
          "nsec": 0
        },
        "frame_id": "map"
      },
      "pose": {
        "position": {
          "x": 0.6559508646656389,
          "y": -1.1781152949374507,
          "z": 0.0
        },
        "orientation": {
          "x": 0.0,
          "y": 0.0,
          "z": 0.0,
          "w": 0.0
        }
      }
    },
    {
      "header": {
        "seq": 0,
        "stamp": {
          "sec": 0,
          "nsec": 0
        },
        "frame_id": "map"
      },
      "pose": {
        "position": {
          "x": 0.6803328406604254,
          "y": -1.0871205217359814,
          "z": 0.0
        },
        "orientation": {
          "x": 0.0,
          "y": 0.0,
          "z": 0.0,
          "w": 0.0
        }
      }
    },
    {
      "header": {
        "seq": 0,
        "stamp": {
          "sec": 0,
          "nsec": 0
        },
        "frame_id": "map"
      },
      "pose": {
        "position": {
          "x": 0.6950697058314461,
          "y": -0.9940756169408862,
          "z": 0.0
        },
        "orientation": {
          "x": 0.0,
          "y": 0.0,
          "z": 0.0,
          "w": 0.0
        }
      }
    },
    {
      "header": {
        "seq": 0,
        "stamp": {
          "sec": 0,
          "nsec": 0
        },
        "frame_id": "map"
      },
      "pose": {
        "position": {
          "x": 0.7,
          "y": -0.899999999999998,
          "z": 0.0
        },
        "orientation": {
          "x": 0.0,
          "y": 0.0,
          "z": 0.0,
          "w": 0.0
        }
      }
    },
    {
      "header": {
        "seq": 0,
        "stamp": {
          "sec": 0,
          "nsec": 0
        },
        "frame_id": "map"
      },
      "pose": {
        "position": {
          "x": 0.6950697058314457,
          "y": -0.80592438305911,
          "z": 0.0
        },
        "orientation": {
          "x": 0.0,
          "y": 0.0,
          "z": 0.0,
          "w": 0.0
        }
      }
    },
    {
      "header": {
        "seq": 0,
        "stamp": {
          "sec": 0,
          "nsec": 0
        },
        "frame_id": "map"
      },
      "pose": {
        "position": {
          "x": 0.6803328406604245,
          "y": -0.7128794782640147,
          "z": 0.0
        },
        "orientation": {
          "x": 0.0,
          "y": 0.0,
          "z": 0.0,
          "w": 0.0
        }
      }
    },
    {
      "header": {
        "seq": 0,
        "stamp": {
          "sec": 0,
          "nsec": 0
        },
        "frame_id": "map"
      },
      "pose": {
        "position": {
          "x": 0.6559508646656376,
          "y": -0.6218847050625456,
          "z": 0.0
        },
        "orientation": {
          "x": 0.0,
          "y": 0.0,
          "z": 0.0,
          "w": 0.0
        }
      }
    },
    {
      "header": {
        "seq": 0,
        "stamp": {
          "sec": 0,
          "nsec": 0
        },
        "frame_id": "map"
      },
      "pose": {
        "position": {
          "x": 0.62219091187834,
          "y": -0.533937021231778,
          "z": 0.0
        },
        "orientation": {
          "x": 0.0,
          "y": 0.0,
          "z": 0.0,
          "w": 0.0
        }
      }
    },
    {
      "header": {
        "seq": 0,
        "stamp": {
          "sec": 0,
          "nsec": 0
        },
        "frame_id": "map"
      },
      "pose": {
        "position": {
          "x": 0.5794228634059939,
          "y": -0.4499999999999983,
          "z": 0.0
        },
        "orientation": {
          "x": 0.0,
          "y": 0.0,
          "z": 0.0,
          "w": 0.0
        }
      }
    },
    {
      "header": {
        "seq": 0,
        "stamp": {
          "sec": 0,
          "nsec": 0
        },
        "frame_id": "map"
      },
      "pose": {
        "position": {
          "x": 0.5281152949374515,
          "y": -0.37099327293677253,
          "z": 0.0
        },
        "orientation": {
          "x": 0.0,
          "y": 0.0,
          "z": 0.0,
          "w": 0.0
        }
      }
    },
    {
      "header": {
        "seq": 0,
        "stamp": {
          "sec": 0,
          "nsec": 0
        },
        "frame_id": "map"
      },
      "pose": {
        "position": {
          "x": 0.4688303429296535,
          "y": -0.2977824542770261,
          "z": 0.0
        },
        "orientation": {
          "x": 0.0,
          "y": 0.0,
          "z": 0.0,
          "w": 0.0
        }
      }
    },
    {
      "header": {
        "seq": 0,
        "stamp": {
          "sec": 0,
          "nsec": 0
        },
        "frame_id": "map"
      },
      "pose": {
        "position": {
          "x": 0.4022175457229709,
          "y": -0.23116965707034376,
          "z": 0.0
        },
        "orientation": {
          "x": 0.0,
          "y": 0.0,
          "z": 0.0,
          "w": 0.0
        }
      }
    },
    {
      "header": {
        "seq": 0,
        "stamp": {
          "sec": 0,
          "nsec": 0
        },
        "frame_id": "map"
      },
      "pose": {
        "position": {
          "x": 0.32900672706322415,
          "y": -0.17188470506254605,
          "z": 0.0
        },
        "orientation": {
          "x": 0.0,
          "y": 0.0,
          "z": 0.0,
          "w": 0.0
        }
      }
    },
    {
      "header": {
        "seq": 0,
        "stamp": {
          "sec": 0,
          "nsec": 0
        },
        "frame_id": "map"
      },
      "pose": {
        "position": {
          "x": 0.24999999999999822,
          "y": -0.12057713659400415,
          "z": 0.0
        },
        "orientation": {
          "x": 0.0,
          "y": 0.0,
          "z": 0.0,
          "w": 0.0
        }
      }
    },
    {
      "header": {
        "seq": 0,
        "stamp": {
          "sec": 0,
          "nsec": 0
        },
        "frame_id": "map"
      },
      "pose": {
        "position": {
          "x": 0.16606297876821835,
          "y": -0.07780908812165832,
          "z": 0.0
        },
        "orientation": {
          "x": 0.0,
          "y": 0.0,
          "z": 0.0,
          "w": 0.0
        }
      }
    },
    {
      "header": {
        "seq": 0,
        "stamp": {
          "sec": 0,
          "nsec": 0
        },
        "frame_id": "map"
      },
      "pose": {
        "position": {
          "x": 0.07811529493745079,
          "y": -0.04404913533436128,
          "z": 0.0
        },
        "orientation": {
          "x": 0.0,
          "y": 0.0,
          "z": 0.0,
          "w": 0.0
        }
      }
    },
    {
      "header": {
        "seq": 0,
        "stamp": {
          "sec": 0,
          "nsec": 0
        },
        "frame_id": "map"
      },
      "pose": {
        "position": {
          "x": -0.012879478264018446,
          "y": -0.019667159339574636,
          "z": 0.0
        },
        "orientation": {
          "x": 0.0,
          "y": 0.0,
          "z": 0.0,
          "w": 0.0
        }
      }
    },
    {
      "header": {
        "seq": 0,
        "stamp": {
          "sec": 0,
          "nsec": 0
        },
        "frame_id": "map"
      },
      "pose": {
        "position": {
          "x": -0.10592438305911368,
          "y": -0.004930294168553839,
          "z": 0.0
        },
        "orientation": {
          "x": 0.0,
          "y": 0.0,
          "z": 0.0,
          "w": 0.0
        }
      }
    },
    {
      "header": {
        "seq": 0,
        "stamp": {
          "sec": 0,
          "nsec": 0
        },
        "frame_id": "map"
      },
      "pose": {
        "position": {
          "x": -0.20000000000000176,
          "y": 0.0,
          "z": 0.0
        },
        "orientation": {
          "x": 0.0,
          "y": 0.0,
          "z": 0.0,
          "w": 0.0
        }
      }
    }
  ]
}